mkdocs_rtd_dropdown-1.0.2.dist-info/METADATA
mkdocs_rtd_dropdown-1.0.2.dist-info/RECORD
mkdocs_rtd_dropdown-1.0.2.dist-info/WHEEL
mkdocs_rtd_dropdown-1.0.2.dist-info/entry_points.txt
mkdocs_rtd_dropdown-1.0.2.dist-info/top_level.txt
rtd_dropdown/404.html
rtd_dropdown/__init__.py
rtd_dropdown/base.html
rtd_dropdown/breadcrumbs.html
rtd_dropdown/footer.html
rtd_dropdown/main.html
rtd_dropdown/mkdocs_theme.yml
rtd_dropdown/nav.html
rtd_dropdown/search.html
rtd_dropdown/searchbox.html
rtd_dropdown/toc.html
rtd_dropdown/versions.html
rtd_dropdown/css/theme.css
rtd_dropdown/css/theme_extra.css
rtd_dropdown/fonts/fontawesome-webfont.eot
rtd_dropdown/fonts/fontawesome-webfont.svg
rtd_dropdown/fonts/fontawesome-webfont.ttf
rtd_dropdown/fonts/fontawesome-webfont.woff
rtd_dropdown/img/favicon.ico
rtd_dropdown/js/jquery-2.1.1.min.js
rtd_dropdown/js/modernizr-2.8.3.min.js
rtd_dropdown/js/theme.js
